stirrups/__init__.py
stirrups/app.py
stirrups/context.py
stirrups/exceptions.py
stirrups/injection.py
stirrups/logging.py
stirrups/utils.py
stirrups-0.1.3.dist-info/LICENSE
stirrups-0.1.3.dist-info/METADATA
stirrups-0.1.3.dist-info/WHEEL
stirrups-0.1.3.dist-info/top_level.txt
stirrups-0.1.3.dist-info/RECORD
